Metadata-Version: 2.1
Name: GeneSigNet
Version: 0.1.0
Summary: Construct Gene-Signature Network
Home-page: https://github.com/ncbi/GeneSigNet
Author: Bayarbaatar Amgalan
Author-email: bayarbaatar.amgalan@nih.gov
License: UNKNOWN
Platform: UNKNOWN
